grepenv/__main__.py
grepenv/cli.py
grepenv/grepenv.py
grepenv-1.1.1.dist-info/LICENSE
grepenv-1.1.1.dist-info/METADATA
grepenv-1.1.1.dist-info/WHEEL
grepenv-1.1.1.dist-info/entry_points.txt
grepenv-1.1.1.dist-info/RECORD
