Metadata-Version: 2.1
Name: grepenv
Version: 1.1.1
Summary: grep's the env
Home-page: https://github.com/mdLafrance/grepenv
Author: mdLafrance
Author-email: maxlafrance97@gmail.com
Requires-Python: >=3.8,<4.0
Classifier: Programming Language :: Python :: 3
Classifier: Programming Language :: Python :: 3.8
Classifier: Programming Language :: Python :: 3.9
Classifier: Programming Language :: Python :: 3.10
Classifier: Programming Language :: Python :: 3.11
Classifier: Programming Language :: Python :: 3.12
Classifier: Programming Language :: Python :: 3.13
Requires-Dist: rich (>=13.7.0,<14.0.0)
Requires-Dist: typer (>=0.9.0,<0.10.0)
Project-URL: Repository, https://github.com/mdLafrance/grepenv
